specrend/__init__.py
specrend/cietables.py
specrend-0.0.2.dist-info/LICENSE
specrend-0.0.2.dist-info/METADATA
specrend-0.0.2.dist-info/WHEEL
specrend-0.0.2.dist-info/top_level.txt
specrend-0.0.2.dist-info/RECORD
