Metadata-Version: 2.1
Name: specrend
Version: 0.0.2
Summary: A tool to transform spectral images into RGB representation.
Home-page: https://github.com/d70-t/specrend
Author: Tobias Kölling
Author-email: tobias.koelling@physik.uni-muenchen.de
License: UNKNOWN
Platform: UNKNOWN
Classifier: Programming Language :: Python :: 3
Classifier: License :: OSI Approved :: MIT License
Classifier: Operating System :: OS Independent
Requires-Python: >=3
Requires-Dist: numpy
